Metadata-Version: 2.1
Name: ConfigurationsProvider
Version: 0.0.1
Summary: load configurations
Home-page: https://github.com/0xAlon
Download-URL: https://github.com/CarRace/Infrastructure/releases/tag/0.0.1
Author: 0xAlon
Author-email: alon.ttp@gmail.com
License: MIT
Keywords: configurations,ConfigurationsProvider,ConfigurationsProvider
Classifier: Development Status :: 4 - Beta
Classifier: Intended Audience :: Developers
Classifier: Topic :: Software Development :: Build Tools
Classifier: License :: OSI Approved :: MIT License
Classifier: Programming Language :: Python :: 3
Classifier: Programming Language :: Python :: 3.4
Classifier: Programming Language :: Python :: 3.5
Classifier: Programming Language :: Python :: 3.6
Classifier: Programming Language :: Python :: 3.7
Classifier: Programming Language :: Python :: 3.8
Classifier: Programming Language :: Python :: 3.9
Classifier: Programming Language :: Python :: 3.10
Classifier: Programming Language :: Python :: 3.11
License-File: LICENSE.txt
